voispark_mcp/__init__.py
voispark_mcp/__main__.py
voispark_mcp/main.py
voispark_mcp/api/__init__.py
voispark_mcp/api/conversation.py
voispark_mcp/api/history.py
voispark_mcp/api/tts.py
voispark_mcp/api/voice_changer.py
voispark_mcp/api/voice_clone.py
voispark_mcp/api/voices.py
voispark_mcp/core/__init__.py
voispark_mcp/core/api_request.py
voispark_mcp/core/error_code.py
voispark_mcp/msg/__init__.py
voispark_mcp/msg/audio_msg.py
voispark_mcp/msg/base_resp.py
voispark_mcp/msg/conversation_msg.py
voispark_mcp/msg/history_msg.py
voispark_mcp/msg/tts_msg.py
voispark_mcp/msg/voice_changer_msg.py
voispark_mcp/msg/voice_clone_msg.py
voispark_mcp/msg/voices_msg.py
voispark_mcp-0.0.2.dist-info/METADATA
voispark_mcp-0.0.2.dist-info/WHEEL
voispark_mcp-0.0.2.dist-info/entry_points.txt
voispark_mcp-0.0.2.dist-info/licenses/LICENSE
voispark_mcp-0.0.2.dist-info/RECORD
