Metadata-Version: 2.4
Name: voispark-mcp
Version: 0.0.2
Summary: A Model Context Protocol (MCP) project for VoiSpark.
Maintainer-email: SkywalkerDarren <yh322yh@outlook.com>
License: MIT
License-File: LICENSE
Keywords: change-voice,conversation,text-to-speech,tts,voice-changer,voice-clone,voice-cloning,voispark
Classifier: Development Status :: 1 - Planning
Classifier: Intended Audience :: Developers
Classifier: License :: OSI Approved :: MIT License
Classifier: Programming Language :: Python :: 3
Classifier: Programming Language :: Python :: 3.11
Requires-Python: >=3.11
Requires-Dist: aiohttp>=3.11.18
Requires-Dist: dotenv>=0.9.9
Requires-Dist: mcp[cli]>=1.9.0
Requires-Dist: pydantic>=2.11.4
